TUMMET/__init__.py
TUMMET/Fatigue/Analysis.py
TUMMET/Fatigue/Fitting.py
TUMMET/Fatigue/Plotting.py
TUMMET/Fatigue/__init__.py
TUMMET/Tensile/Analysis.py
TUMMET/Tensile/Fitting.py
TUMMET/Tensile/Plotting.py
TUMMET/Tensile/__init__.py
TUMMET-0.0.12.dist-info/LICENSE
TUMMET-0.0.12.dist-info/METADATA
TUMMET-0.0.12.dist-info/WHEEL
TUMMET-0.0.12.dist-info/top_level.txt
TUMMET-0.0.12.dist-info/RECORD
