Metadata-Version: 2.1
Name: TUMMET
Version: 0.0.12
Summary: A packages to evaluate material test data
Home-page: https://github.com/mbwinkler/TUM-MET
Author: Michael Winkler
Author-email: michael.b.winkler@tum.de
License: UNKNOWN
Platform: UNKNOWN
Classifier: Programming Language :: Python :: 3
Classifier: License :: OSI Approved :: BSD License
Classifier: Operating System :: OS Independent
Requires-Python: >=3.9
License-File: LICENSE
Requires-Dist: colorama (==0.4.4)
Requires-Dist: cycler (==0.11.0)
Requires-Dist: et-xmlfile (==1.1.0)
Requires-Dist: fonttools (==4.32.0)
Requires-Dist: kiwisolver (==1.4.2)
Requires-Dist: matplotlib (==3.5.1)
Requires-Dist: numpy (==1.22.3)
Requires-Dist: openpyxl (==3.0.9)
Requires-Dist: packaging (==21.3)
Requires-Dist: pandas (==1.4.2)
Requires-Dist: Pillow (==9.1.0)
Requires-Dist: pyparsing (==3.0.8)
Requires-Dist: python-dateutil (==2.8.2)
Requires-Dist: pytz (==2022.1)
Requires-Dist: scipy (==1.8.0)
Requires-Dist: seaborn (==0.11.2)
Requires-Dist: six (==1.16.0)
Requires-Dist: tqdm (==4.64.0)
